Blue2Factor/Authentication.py
Blue2Factor/__init__.py
Blue2Factor/tests/__init__.py
Blue2FactorPy-0.1.3.dist-info/LICENSE
Blue2FactorPy-0.1.3.dist-info/METADATA
Blue2FactorPy-0.1.3.dist-info/WHEEL
Blue2FactorPy-0.1.3.dist-info/top_level.txt
Blue2FactorPy-0.1.3.dist-info/RECORD
