Metadata-Version: 2.1
Name: Blue2FactorPy
Version: 0.1.3
Summary: Used to implement Blue2Factor
Home-page: https://www.blue2factor.com
Author: Christopher McLain
Author-email: chris@blue2factor.com
License: UNKNOWN
Project-URL: Bug Tracker, https://github.com/bk89686/blue2factorpy/issues
Platform: UNKNOWN
Classifier: Programming Language :: Python :: 3
Classifier: License :: OSI Approved :: MIT License
Classifier: Operating System :: OS Independent
Requires-Python: >=3.6
License-File: LICENSE
